{
  "hashtag_stats": {
    "nifty50": {
      "collected": 6,
      "unique": 6,
      "target": 2,
      "percentage": 300.0
    },
    "sensex": {
      "collected": 8,
      "unique": 5,
      "target": 2,
      "percentage": 400.0
    },
    "intraday": {
      "collected": 7,
      "unique": 7,
      "target": 2,
      "percentage": 350.0
    },
    "banknifty": {
      "collected": 8,
      "unique": 6,
      "target": 2,
      "percentage": 400.0
    }
  },
  "global_stats": {
    "unique_tweets": 24,
    "duplicates_skipped": 5,
    "total_processed": 29,
    "deduplication_rate": 17.24137931034483
  },
  "rate_limiter_stats": {
    "current_rate": 10.0,
    "min_rate": 1.0,
    "max_rate": 20.0,
    "rate_limit_count": 0,
    "success_count": 8,
    "name": "default",
    "rate": 10.0,
    "capacity": 20,
    "current_tokens": 19,
    "utilization": 5.000000000000004
  },
  "processing_stats": {
    "processed": 24,
    "errors": 0,
    "success_rate": 100.0
  }
}